exapp/ExampleApp.py
exapp/__init__.py
exapp/__main__.py
exapp/exampleLoaderTemplate_generic.py
exapp/image_as_py.py
exapp/utils.py
exapp-0.2.1.dist-info/entry_points.txt
exapp-0.2.1.dist-info/LICENSE
exapp-0.2.1.dist-info/WHEEL
exapp-0.2.1.dist-info/METADATA
exapp-0.2.1.dist-info/RECORD
