Metadata-Version: 2.1
Name: exapp
Version: 0.2.1
Summary: A Python Example Launcher Application
Keywords: example,gui,application
Author-email: Euiyun Edwin Kim <geniuskey@gmail.com>
Requires-Python: >=3.7
Classifier: License :: OSI Approved :: MIT License
Classifier: Operating System :: OS Independent
Classifier: Programming Language :: Python
Classifier: Programming Language :: Python :: 3 :: Only
Classifier: Programming Language :: Python :: 3.7
Classifier: Programming Language :: Python :: 3.8
Classifier: Programming Language :: Python :: 3.9
Classifier: Programming Language :: Python :: 3.10
Classifier: Programming Language :: Python :: 3.11
Classifier: Programming Language :: Python :: 3.12
Requires-Dist: pyqtgraph>=0.12
Requires-Dist: colorama>=0.4.4; sys_platform == "win32"
Requires-Dist: tomli; python_version < "3.11"
Requires-Dist: sphinx ; extra == "doc"
Requires-Dist: sphinx-rtd-theme ; extra == "doc"
Requires-Dist: PyQt5 ; extra == "gui"
Requires-Dist: PySide2 ; extra == "gui"
Project-URL: Documentation, https://exapp.readthedocs.io
Project-URL: Repository, https://github.com/allinpy/ExApp.git
Provides-Extra: doc
Provides-Extra: gui
